{
  "majors": [
    {
      "id": 1,
      "name": "C Major",
      "notes": ["C", "D", "E", "F", "G", "A", "B"]
    },
    {
      "id": 2,
      "name": "D Major",
      "notes": ["D", "E", "F#", "G", "A", "B", "C#"]
    },
    {
      "id": 3,
      "name": "E Major",
      "notes": ["E", "F#", "G#", "A", "B", "C#", "D#"]
    },
    {
      "id": 4,
      "name": "F Major",
      "notes": ["F", "G", "A", "Bb", "C", "D", "E"]
    },
    {
      "id": 5,
      "name": "G Major",
      "notes": ["G", "A", "B", "C", "D", "E", "F#"]
    },
    {
      "id": 6,
      "name": "A Major",
      "notes": ["A", "B", "C#", "D", "E", "F#", "G#"]
    },
    {
      "id": 7,
      "name": "B Major",
      "notes": ["B", "C#", "D#", "E", "F#", "G#", "A#"]
    },
    {
      "id": 8,
      "name": "C#/Db Major",
      "notes": ["Db", "Eb", "F", "Gb", "Ab", "Bb", "C"]
    },
    {
      "id": 9,
      "name": "D#/Eb Major",
      "notes": ["Eb", "F", "G", "Ab", "Bb", "C", "D"]
    },
    {
      "id": 10,
      "name": "F#/Gb Major",
      "notes": ["F#", "G#", "A#", "B", "C#", "D#", "E#"]
    },
    {
      "id": 11,
      "name": "G#/Ab Major",
      "notes": ["Ab", "Bb", "C", "Db", "Eb", "F", "G"]
    },
    {
      "id": 12,
      "name": "A#/Bb Major",
      "notes": ["Bb", "C", "D", "Eb", "F", "G", "A"]
    }
  ],
  "minors": [
    {
      "id": 1,
      "name": "C Minor",
      "notes": ["C", "D", "Eb", "F", "G", "Ab", "Bb"]
    },
    {
      "id": 2,
      "name": "D Minor",
      "notes": ["D", "E", "F", "G", "A", "Bb", "C"]
    },
    {
      "id": 3,
      "name": "E Minor",
      "notes": ["E", "F#", "G", "A", "B", "C", "D"]
    },
    {
      "id": 4,
      "name": "F Minor",
      "notes": ["F", "G", "Ab", "Bb", "C", "Db", "Eb"]
    },
    {
      "id": 5,
      "name": "G Minor",
      "notes": ["G", "A", "Bb", "C", "D", "Eb", "F"]
    },
    {
      "id": 6,
      "name": "A Minor",
      "notes": ["A", "B", "C", "D", "E", "F", "G"]
    },
    {
      "id": 7,
      "name": "B Minor",
      "notes": ["B", "C#", "D", "E", "F#", "G", "A"]
    },
    {
      "id": 8,
      "name": "C#/Db Minor",
      "notes": ["Db", "Eb", "E", "Gb", "Ab", "A", "B"]
    },
    {
      "id": 9,
      "name": "D#/Eb Minor",
      "notes": ["D#", "E#", "F#", "G#", "A#", "B", "C#"]
    },
    {
      "id": 10,
      "name": "F#/Gb Minor",
      "notes": ["F#", "G#", "A", "B", "C#", "D", "E"]
    },
    {
      "id": 11,
      "name": "G#/Ab Minor",
      "notes": ["G#", "A#", "B", "C#", "D#", "E", "F#"]
    },
    {
      "id": 12,
      "name": "A#/Bb Minor",
      "notes": ["Bb", "C", "Db", "Eb", "F", "Gb", "Ab"]
    }
  ]
}
